plugin_test_inven_collector/__about__.py
plugin_test_inven_collector/__init__.py
plugin_test_inven_collector/main.py
plugin_test_inven_collector-1.0.0.dist-info/METADATA
plugin_test_inven_collector-1.0.0.dist-info/WHEEL
plugin_test_inven_collector-1.0.0.dist-info/RECORD
