Metadata-Version: 2.1
Name: plugin-test-inven-collector
Version: 1.0.0
Summary: This is a plugin for testing hatch
Project-URL: Documentation, https://github.com/unknown/plugin-test-inven-collector#readme
Project-URL: Issues, https://github.com/unknown/plugin-test-inven-collector/issues
Project-URL: Source, https://github.com/unknown/plugin-test-inven-collector
Author-email: Youngjin Jo <yjinjo@berkeley.edu>
License-Expression: MIT
Classifier: Development Status :: 4 - Beta
Classifier: Programming Language :: Python
Classifier: Programming Language :: Python :: 3.8
Classifier: Programming Language :: Python :: 3.9
Classifier: Programming Language :: Python :: 3.10
Classifier: Programming Language :: Python :: 3.11
Classifier: Programming Language :: Python :: 3.12
Classifier: Programming Language :: Python :: Implementation :: CPython
Classifier: Programming Language :: Python :: Implementation :: PyPy
Requires-Python: >=3.8
